odoo10_addon_mail_sendgrid-10.0.1.0.3-py3.8-nspkg.pth
odoo/addons/mail_sendgrid/README.rst
odoo/addons/mail_sendgrid/__init__.py
odoo/addons/mail_sendgrid/__manifest__.py
odoo/addons/mail_sendgrid/controllers/__init__.py
odoo/addons/mail_sendgrid/controllers/json_request.py
odoo/addons/mail_sendgrid/controllers/sendgrid_event_webhook.py
odoo/addons/mail_sendgrid/i18n/mail_sendgrid.pot
odoo/addons/mail_sendgrid/models/__init__.py
odoo/addons/mail_sendgrid/models/email_lang_template.py
odoo/addons/mail_sendgrid/models/email_template.py
odoo/addons/mail_sendgrid/models/email_tracking.py
odoo/addons/mail_sendgrid/models/mail_mail.py
odoo/addons/mail_sendgrid/models/mail_tracking_event.py
odoo/addons/mail_sendgrid/models/sendgrid_template.py
odoo/addons/mail_sendgrid/models/substitution.py
odoo/addons/mail_sendgrid/security/ir.model.access.csv
odoo/addons/mail_sendgrid/static/description/icon.png
odoo/addons/mail_sendgrid/static/description/icon.svg
odoo/addons/mail_sendgrid/tests/__init__.py
odoo/addons/mail_sendgrid/tests/test_mail_sendgrid.py
odoo/addons/mail_sendgrid/views/email_template_view.xml
odoo/addons/mail_sendgrid/views/mail_compose_message_view.xml
odoo/addons/mail_sendgrid/views/sendgrid_email_view.xml
odoo/addons/mail_sendgrid/views/sendgrid_template_view.xml
odoo/addons/mail_sendgrid/wizards/__init__.py
odoo/addons/mail_sendgrid/wizards/email_template_preview.py
odoo/addons/mail_sendgrid/wizards/mail_compose_message.py
odoo10_addon_mail_sendgrid-10.0.1.0.3.dist-info/METADATA
odoo10_addon_mail_sendgrid-10.0.1.0.3.dist-info/WHEEL
odoo10_addon_mail_sendgrid-10.0.1.0.3.dist-info/namespace_packages.txt
odoo10_addon_mail_sendgrid-10.0.1.0.3.dist-info/top_level.txt
odoo10_addon_mail_sendgrid-10.0.1.0.3.dist-info/RECORD
